{
  "name": "Leech",
  "type": "npc_feature",
  "system": {
    "lid": "npc_Leech_Leech",
    "effect": "The Leech has improved grappling capabilities. This grants the following benefits:<p>The Leech can grapple within range 3. When it grapples a character, remove the Leech from the battlefield. It counts as sharing that character's space. This doesn’t provoke reactions and ignores engagement.</p><p>1/round, the Leech may grapple as a free action. When grappling an allied character, it automatically succeeds.</p><p>The Leech can perform reactions while Grappled. Allied characters can take reactions and Boost while grappled by the Leech.</p><p>While grappling a character, the Leech has soft cover. A Grappled allied character also has soft cover.</p><p>The Leech may begin the combat already Grappling an allied character.</p>",
    "bonus": {
      "activations": null,
      "armor": null,
      "hp": null,
      "evasion": null,
      "edef": null,
      "heatcap": null,
      "speed": null,
      "sensor_range": null,
      "save": null,
      "hull": null,
      "agi": null,
      "sys": null,
      "eng": null,
      "size": null,
      "structure": null,
      "stress": null
    },
    "override": {
      "activations": null,
      "armor": null,
      "hp": null,
      "evasion": null,
      "edef": null,
      "heatcap": null,
      "speed": null,
      "sensor_range": null,
      "save": null,
      "hull": null,
      "agi": null,
      "sys": null,
      "eng": null,
      "size": null,
      "structure": null,
      "stress": null
    },
    "tags": [],
    "type": "Trait",
    "origin": {
      "name": "Leech",
      "type": "Class",
      "base": true
    },
    "charged": false,
    "uses": 0,
    "loaded": false,
    "destroyed": false,
    "tier_override": 0,
    "tech_attack": false,
    "damage": [],
    "range": [],
    "on_hit": "",
    "accuracy": [
      0,
      0,
      0
    ],
    "attack_bonus": [
      0,
      0,
      0
    ],
    "tech_type": "Quick",
    "cascading": false
  },
  "folder": "iU14HkPHRVW82mzf",
  "_id": "xYhUzIGobH5kqIsv",
  "img": "systems/lancer/assets/icons/generic_item.svg",
  "effects": [],
  "sort": 0,
  "ownership": {
    "default": 0,
    "YArGKa3f4FYWoPpm": 3
  },
  "flags": {},
  "_stats": {
    "compendiumSource": null,
    "duplicateSource": null,
    "coreVersion": "12.331",
    "systemId": "lancer",
    "systemVersion": "2.8.1",
    "createdTime": 1747636694188,
    "modifiedTime": 1747636694188,
    "lastModifiedBy": "YArGKa3f4FYWoPpm"
  }
}