{
  "name": "PRIMARY WEAPON",
  "type": "npc_feature",
  "system": {
    "lid": "npcf_primary_weapon_squad",
    "effect": "This weapon can make two attacks at a time; if the Squad loses more than half its HP, it can only make one attack at a time.",
    "bonus": {
      "activations": null,
      "armor": null,
      "hp": null,
      "evasion": null,
      "edef": null,
      "heatcap": null,
      "speed": null,
      "sensor_range": null,
      "save": null,
      "hull": null,
      "agi": null,
      "sys": null,
      "eng": null,
      "size": null,
      "structure": null,
      "stress": null
    },
    "override": {
      "activations": null,
      "armor": null,
      "hp": null,
      "evasion": null,
      "edef": null,
      "heatcap": null,
      "speed": null,
      "sensor_range": null,
      "save": null,
      "hull": null,
      "agi": null,
      "sys": null,
      "eng": null,
      "size": null,
      "structure": null,
      "stress": null
    },
    "tags": [],
    "type": "Weapon",
    "origin": {
      "type": "Class",
      "name": "SQUAD",
      "base": true
    },
    "charged": false,
    "uses": 0,
    "loaded": false,
    "destroyed": false,
    "tier_override": 0,
    "accuracy": [
      0,
      0,
      0
    ],
    "attack_bonus": [
      2,
      4,
      6
    ],
    "weapon_type": "Main Rifle",
    "on_hit": "",
    "damage": [
      [
        {
          "type": "Variable",
          "val": "2"
        }
      ],
      [
        {
          "type": "Variable",
          "val": "3"
        }
      ],
      [
        {
          "type": "Variable",
          "val": "4"
        }
      ]
    ],
    "range": [
      {
        "type": "Range",
        "val": 5
      }
    ],
    "tech_attack": false,
    "tech_type": "Quick",
    "cascading": false
  },
  "folder": "iU14HkPHRVW82mzf",
  "_id": "G7Xk0ZcFAixnAEra",
  "img": "systems/lancer/assets/icons/generic_item.svg",
  "effects": [],
  "sort": 0,
  "ownership": {
    "default": 0,
    "YArGKa3f4FYWoPpm": 3
  },
  "flags": {},
  "_stats": {
    "compendiumSource": null,
    "duplicateSource": null,
    "coreVersion": "12.331",
    "systemId": "lancer",
    "systemVersion": "2.8.1",
    "createdTime": 1747636604568,
    "modifiedTime": 1747636604568,
    "lastModifiedBy": "YArGKa3f4FYWoPpm"
  }
}