{
  "name": "Access",
  "type": "reserve",
  "system": {
    "lid": "reserve_access",
    "description": "A keycard, invite, bribes or insider access to a particular location.",
    "actions": [],
    "bonuses": [],
    "consumable": false,
    "counters": [],
    "deployables": [],
    "integrated": [],
    "label": "Resource",
    "synergies": [],
    "tags": [],
    "type": "Tactical",
    "used": false
  },
  "folder": "z0MYVYjPQHigOgT5",
  "_id": "x0QDoy5ByhVhmOid",
  "img": "systems/lancer/assets/icons/reserve_tac.svg",
  "effects": [],
  "sort": 0,
  "ownership": {
    "default": 0,
    "YArGKa3f4FYWoPpm": 3
  },
  "flags": {},
  "_stats": {
    "compendiumSource": null,
    "duplicateSource": null,
    "coreVersion": "12.331",
    "systemId": "lancer",
    "systemVersion": "2.8.1",
    "createdTime": 1747537556080,
    "modifiedTime": 1747537556080,
    "lastModifiedBy": "YArGKa3f4FYWoPpm"
  }
}